difflicious/__init__.py
difflicious/app.py
difflicious/cli.py
difflicious/diff_parser.py
difflicious/dummy_data.json
difflicious/git_operations.py
difflicious/services/__init__.py
difflicious/services/base_service.py
difflicious/services/diff_service.py
difflicious/services/exceptions.py
difflicious/services/git_service.py
difflicious/services/syntax_service.py
difflicious/services/template_service.py
difflicious/static/css/styles.css
difflicious/static/css/tailwind.css
difflicious/static/css/tailwind.input.css
difflicious/static/js/app.js
difflicious/static/js/diff-interactions.js
difflicious/templates/base.html
difflicious/templates/diff_file.html
difflicious/templates/diff_groups.html
difflicious/templates/diff_hunk.html
difflicious/templates/index.html
difflicious/templates/partials/empty_state.html
difflicious/templates/partials/global_controls.html
difflicious/templates/partials/loading_state.html
difflicious/templates/partials/toolbar.html
difflicious-0.9.2.dist-info/METADATA
difflicious-0.9.2.dist-info/WHEEL
difflicious-0.9.2.dist-info/entry_points.txt
difflicious-0.9.2.dist-info/licenses/LICENSE
difflicious-0.9.2.dist-info/RECORD
