Metadata-Version: 2.4
Name: difflicious
Version: 0.9.2
Summary: A sleek web-based git diff visualization tool for developers
Project-URL: Homepage, https://github.com/insipid/difflicious
Project-URL: Repository, https://github.com/insipid/difflicious
Project-URL: Issues, https://github.com/insipid/difflicious/issues
Author-email: Drew <noreply@example.com>
License: MIT
License-File: LICENSE
Keywords: development,diff,git,visualization,web
Classifier: Development Status :: 3 - Alpha
Classifier: Intended Audience :: Developers
Classifier: License :: OSI Approved :: MIT License
Classifier: Programming Language :: Python :: 3
Classifier: Programming Language :: Python :: 3.9
Classifier: Programming Language :: Python :: 3.10
Classifier: Programming Language :: Python :: 3.11
Classifier: Programming Language :: Python :: 3.12
Classifier: Topic :: Software Development :: Version Control :: Git
Classifier: Topic :: Text Processing :: General
Requires-Python: >=3.9
Requires-Dist: click>=8.0.0
Requires-Dist: flask>=2.3.0
Requires-Dist: jinja-partials>=0.2.0
Requires-Dist: markupsafe>=2.1.0
Requires-Dist: pygments>=2.17.0
Requires-Dist: unidiff>=0.7.5
Provides-Extra: dev
Requires-Dist: black>=23.0.0; extra == 'dev'
Requires-Dist: mypy>=1.0.0; extra == 'dev'
Requires-Dist: pytest-cov>=4.0.0; extra == 'dev'
Requires-Dist: pytest>=7.0.0; extra == 'dev'
Requires-Dist: ruff>=0.1.0; extra == 'dev'
